ansys/dynamicreporting/core/__init__.py
ansys/dynamicreporting/core/_version.py
ansys/dynamicreporting/core/adr_item.py
ansys/dynamicreporting/core/adr_report.py
ansys/dynamicreporting/core/adr_service.py
ansys/dynamicreporting/core/adr_utils.py
ansys/dynamicreporting/core/build_info.py
ansys/dynamicreporting/core/common_utils.py
ansys/dynamicreporting/core/constants.py
ansys/dynamicreporting/core/docker_support.py
ansys/dynamicreporting/core/exceptions.py
ansys/dynamicreporting/core/examples/__init__.py
ansys/dynamicreporting/core/examples/downloads.py
ansys/dynamicreporting/core/serverless/__init__.py
ansys/dynamicreporting/core/serverless/adr.py
ansys/dynamicreporting/core/serverless/base.py
ansys/dynamicreporting/core/serverless/html_exporter.py
ansys/dynamicreporting/core/serverless/item.py
ansys/dynamicreporting/core/serverless/template.py
ansys/dynamicreporting/core/utils/__init__.py
ansys/dynamicreporting/core/utils/encoders.py
ansys/dynamicreporting/core/utils/enhanced_images.py
ansys/dynamicreporting/core/utils/exceptions.py
ansys/dynamicreporting/core/utils/extremely_ugly_hacks.py
ansys/dynamicreporting/core/utils/filelock.py
ansys/dynamicreporting/core/utils/geofile_processing.py
ansys/dynamicreporting/core/utils/html_export_constants.py
ansys/dynamicreporting/core/utils/report_download_html.py
ansys/dynamicreporting/core/utils/report_download_pdf.py
ansys/dynamicreporting/core/utils/report_objects.py
ansys/dynamicreporting/core/utils/report_remote_server.py
ansys/dynamicreporting/core/utils/report_utils.py
ansys_dynamicreporting_core-0.10.6.dist-info/METADATA
ansys_dynamicreporting_core-0.10.6.dist-info/WHEEL
ansys_dynamicreporting_core-0.10.6.dist-info/licenses/AUTHORS
ansys_dynamicreporting_core-0.10.6.dist-info/licenses/LICENSE
ansys_dynamicreporting_core-0.10.6.dist-info/RECORD
