Metadata-Version: 2.4
Name: ansys-dynamicreporting-core
Version: 0.10.6
Summary: Python interface to Ansys Dynamic Reporting
Project-URL: homepage, https://github.com/ansys/pydynamicreporting
Project-URL: documentation, https://dynamicreporting.docs.pyansys.com/
Project-URL: changelog, https://github.com/ansys/pydynamicreporting/blob/main/CHANGELOG.md
Project-URL: repository, https://github.com/ansys/pydynamicreporting
Project-URL: bug_tracker, https://github.com/ansys/pydynamicreporting/issues
Project-URL: ci, https://github.com/ansys/pydynamicreporting/actions
Author-email: "ANSYS, Inc." <pyansys.core@ansys.com>, Ansys ADR Team <adrteam@ansys.com>
Maintainer-email: "ANSYS, Inc." <pyansys.core@ansys.com>, Ansys ADR Team <adrteam@ansys.com>
License: MIT
License-File: AUTHORS
License-File: LICENSE
Keywords: ansys,dynamicreporting,pyansys,pydynamicreporting
Classifier: Development Status :: 4 - Beta
Classifier: Intended Audience :: Developers
Classifier: License :: OSI Approved :: MIT License
Classifier: Natural Language :: English
Classifier: Operating System :: Microsoft :: Windows
Classifier: Operating System :: POSIX :: Linux
Classifier: Programming Language :: Python :: 3.10
Classifier: Programming Language :: Python :: 3.11
Classifier: Programming Language :: Python :: 3.12
Classifier: Topic :: Software Development :: Libraries :: Python Modules
Requires-Python: <3.13,>=3.10
Requires-Dist: bleach>=6.2.0
Requires-Dist: django-guardian<3.0.0,>=2.4.0
Requires-Dist: django-weasyprint<2.5.0,>=2.4.0
Requires-Dist: django<5.0,>=4.2.27
Requires-Dist: djangorestframework<3.16.0,>=3.15.2
Requires-Dist: docker>=7.1.0
Requires-Dist: lark<1.3.0,>=1.2.2
Requires-Dist: numpy<2.0.0,>=1.26.4
Requires-Dist: pandas<3.0.0,>=2.2.2
Requires-Dist: pillow>=9.3.0
Requires-Dist: psutil>=6.0.0
Requires-Dist: psycopg[binary]<3.3.0,>=3.2.6
Requires-Dist: pypng>=0.20220715.0
Requires-Dist: python-dateutil>=2.8.0
Requires-Dist: python-pptx<2.0.0,>=1.0.2
Requires-Dist: pytz>=2021.3
Requires-Dist: qtpy<2.5.0,>=2.4.3
Requires-Dist: requests>=2.32
Requires-Dist: statsmodels<0.15.0,>=0.14.2
Requires-Dist: tzlocal<6.0,>=5.3.1
Requires-Dist: urllib3<3.0.0
Provides-Extra: dev
Requires-Dist: black; extra == 'dev'
Requires-Dist: codespell; extra == 'dev'
Requires-Dist: hatch; extra == 'dev'
Requires-Dist: ipdb; extra == 'dev'
Requires-Dist: isort; extra == 'dev'
Requires-Dist: pip; extra == 'dev'
Requires-Dist: pre-commit; extra == 'dev'
Requires-Dist: twine; extra == 'dev'
Requires-Dist: uv; extra == 'dev'
Provides-Extra: doc
Requires-Dist: ansys-sphinx-theme; extra == 'doc'
Requires-Dist: docutils>=0.21; extra == 'doc'
Requires-Dist: numpydoc; extra == 'doc'
Requires-Dist: sphinx; extra == 'doc'
Requires-Dist: sphinx-copybutton; extra == 'doc'
Requires-Dist: sphinx-gallery; extra == 'doc'
Provides-Extra: test
Requires-Dist: ansys-dpf-core==0.14.2; extra == 'test'
Requires-Dist: pytest; extra == 'test'
Requires-Dist: pytest-cov; extra == 'test'
Requires-Dist: pyvista==0.46.4; extra == 'test'
Requires-Dist: vtk==9.5.2; extra == 'test'
